.gitignore
.gitlab-ci.yml
AUTHORS.md
LICENSE
MANIFEST.in
README.md
RELEASING.md
install.ps1
install.sh
mkdocs.yml
pyproject.toml
requirements.txt
setup.cfg
setup.py
docs/api-docs.md
docs/index.md
docs/install.md
docs/modules.api.md
docs/modules.md
docs/modules.tutorial.md
docs/users.md
docs/api/Makefile
docs/api/conf.py
docs/api/index.rst
docs/example-data/18-06-04_1_ch3.txt
docs/img/application-scheme.pdf
docs/img/application-scheme.png
docs/img/database-connection.png
docs/img/icon.png
docs/img/screenshot.png
docs/img/tutorial-screenshot.png
docs/tutorial/demodataset.txt
docs/tutorial/experiment.py
docs/tutorial/primary.py
docs/tutorial/reader.py
docs/tutorial/secondary.py
iocbio.kinetics.egg-info/PKG-INFO
iocbio.kinetics.egg-info/SOURCES.txt
iocbio.kinetics.egg-info/dependency_links.txt
iocbio.kinetics.egg-info/entry_points.txt
iocbio.kinetics.egg-info/requires.txt
iocbio.kinetics.egg-info/top_level.txt
iocbio/kinetics/__init__.py
iocbio/kinetics/constants.py
iocbio/kinetics/global_vars.py
iocbio/kinetics/app/__init__.py
iocbio/kinetics/app/banova.py
iocbio/kinetics/app/fetch.py
iocbio/kinetics/app/fetch_repeated.py
iocbio/kinetics/app/gui.py
iocbio/kinetics/app/icon.png
iocbio/kinetics/app/icon.svg
iocbio/kinetics/app/splash.png
iocbio/kinetics/calc/__init__.py
iocbio/kinetics/calc/bump.py
iocbio/kinetics/calc/composer.py
iocbio/kinetics/calc/current.py
iocbio/kinetics/calc/explin_fit.py
iocbio/kinetics/calc/generic.py
iocbio/kinetics/calc/linreg.py
iocbio/kinetics/calc/mean_med_std.py
iocbio/kinetics/calc/mm.py
iocbio/kinetics/calc/peakarea.py
iocbio/kinetics/calc/respiration.py
iocbio/kinetics/calc/xy.py
iocbio/kinetics/gui/__init__.py
iocbio/kinetics/gui/custom_widgets.py
iocbio/kinetics/gui/edit_event.py
iocbio/kinetics/gui/experiment_plot.py
iocbio/kinetics/gui/mainwindow.py
iocbio/kinetics/gui/module_selector.py
iocbio/kinetics/gui/open.py
iocbio/kinetics/gui/roi_list.py
iocbio/kinetics/gui/stats_widget.py
iocbio/kinetics/gui/xy_plot.py
iocbio/kinetics/handler/__init__.py
iocbio/kinetics/handler/experiment_generic.py
iocbio/kinetics/handler/roi.py
iocbio/kinetics/io/__init__.py
iocbio/kinetics/io/arguments.py
iocbio/kinetics/io/data.py
iocbio/kinetics/io/db.py
