Metadata-Version: 2.1
Name: iocbio.kinetics
Version: 1.5.0
Summary: IOCBio Kinetics
Home-page: https://sysbio.ioc.ee
Author: IOCBio team
Author-email: iocbio@sysbio.ioc.ee
License: GPLv3
Classifier: Development Status :: 4 - Beta
Classifier: Environment :: X11 Applications :: Qt
Classifier: Intended Audience :: Science/Research
Classifier: Programming Language :: Python :: 3
Classifier: Topic :: Scientific/Engineering
License-File: LICENSE
License-File: AUTHORS.md
